magemaker-0.1.15.dist-info/METADATA
magemaker-0.1.15.dist-info/WHEEL
magemaker-0.1.15.dist-info/entry_points.txt
magemaker-0.1.15.dist-info/licenses/LICENSE
magemaker/__init__.py
magemaker/azure/__init__.py
magemaker/azure/create_model.py
magemaker/azure/delete_model.py
magemaker/azure/query_endpoint.py
magemaker/azure/resources.py
magemaker/azure/test_create_model.py
magemaker/azure/test_delete_model.py
magemaker/azure/test_query_endpoint.py
magemaker/azure/test_resources.py
magemaker/config.py
magemaker/console.py
magemaker/gcp/__init__.py
magemaker/gcp/create_model.py
magemaker/gcp/delete_model.py
magemaker/gcp/query_endpoint.py
magemaker/gcp/resources.py
magemaker/gcp/test_create_model.py
magemaker/gcp/test_delete_model.py
magemaker/gcp/test_query_endpoint.py
magemaker/gcp/test_resources.py
magemaker/huggingface/__init__.py
magemaker/huggingface/hf_hub_api.py
magemaker/main.py
magemaker/runner.py
magemaker/sagemaker/__init__.py
magemaker/sagemaker/create_model.py
magemaker/sagemaker/delete_model.py
magemaker/sagemaker/fine_tune_model.py
magemaker/sagemaker/query_endpoint.py
magemaker/sagemaker/resources.py
magemaker/sagemaker/search_jumpstart_models.py
magemaker/sagemaker/test_resources.py
magemaker/schemas/__init__.py
magemaker/schemas/deployment.py
magemaker/schemas/model.py
magemaker/schemas/query.py
magemaker/schemas/training.py
magemaker/scripts/preflight.sh
magemaker/scripts/setup_role.sh
magemaker/session.py
magemaker/utils/__init__.py
magemaker/utils/aws_utils.py
magemaker/utils/format.py
magemaker/utils/model_utils.py
magemaker/utils/rich_utils.py
magemaker/yaml.py
magemaker-0.1.15.dist-info/RECORD
