Metadata-Version: 2.1
Name: magemaker
Version: 0.1.15
Summary: A CLI tool to fine-tuning and deploying open-source models
Author-Email: eff-kay <faizank@slashml.com>
License: MIT
Requires-Python: >=3.11
Requires-Dist: pyyaml>=6.0.1
Requires-Dist: python-dotenv>=1.0.1
Requires-Dist: rich>=13.7.1
Requires-Dist: sagemaker>=2.218.1
Requires-Dist: boto3>=1.34.99
Requires-Dist: setuptools>=69.5.1
Requires-Dist: huggingface-hub>=0.23.0
Requires-Dist: pydantic>=2.7.1
Requires-Dist: datasets>=2.19.1
Requires-Dist: transformers>=4.40.2
Requires-Dist: inquirer>=3.2.4
Requires-Dist: inquirerpy>=0.3.4
Requires-Dist: uvicorn>=0.29.0
Requires-Dist: fastapi>=0.111.0
Requires-Dist: litellm>=1.37.5
Requires-Dist: google-cloud-aiplatform==1.75.0
Requires-Dist: azure-ai-ml==1.23.0
Requires-Dist: azure-identity==1.19.0
Requires-Dist: azure-mgmt-resource==23.2.0
Requires-Dist: marshmallow==3.23.2
